myevery/__init__.py
myevery/__main__.py
myevery/server/__init__.py
myevery/server/api.py
myevery/static/css/docs.css
myevery/static/img/favicon.png
myevery-0.0.11.dist-info/entry_points.txt
myevery-0.0.11.dist-info/LICENSE
myevery-0.0.11.dist-info/WHEEL
myevery-0.0.11.dist-info/METADATA
myevery-0.0.11.dist-info/RECORD
